github_timeline_rss/__init__.py
github_timeline_rss/cli.py
github_timeline_rss/rss.py
github_timeline_rss/util.py
tests/__init__.py
tests/test_rss.py
github_timeline_rss-1.2.2.dist-info/LICENSE
github_timeline_rss-1.2.2.dist-info/METADATA
github_timeline_rss-1.2.2.dist-info/WHEEL
github_timeline_rss-1.2.2.dist-info/entry_points.txt
github_timeline_rss-1.2.2.dist-info/top_level.txt
github_timeline_rss-1.2.2.dist-info/zip-safe
github_timeline_rss-1.2.2.dist-info/RECORD
