Metadata-Version: 2.1
Name: github-timeline-rss
Version: 1.2.2
Summary: Github timeline to RSS translation for easier feed integration
Home-page: https://github.com/narfman0/github_timeline_rss
Author: Jon Robison
Author-email: narfman0@gmail.com
License: MIT license
Keywords: github_timeline_rss github timeline rss atom
Platform: UNKNOWN
Classifier: Development Status :: 4 - Beta
Classifier: Intended Audience :: Developers
Classifier: License :: OSI Approved :: MIT License
Classifier: Natural Language :: English
Classifier: Programming Language :: Python :: 3
Classifier: Programming Language :: Python :: 3.5
Classifier: Programming Language :: Python :: 3.6
Classifier: Programming Language :: Python :: 3.7
Classifier: Programming Language :: Python :: 3.8
Requires-Dist: flask
Requires-Dist: requests
